just_agents/examples/__init__.py
just_agents/examples/basic/__init__.py
just_agents/examples/basic/agent_profiles.yaml
just_agents/examples/basic/agent_serialization.py
just_agents/examples/basic/chain_of_thought_example.py
just_agents/examples/basic/function_calling_example.py
just_agents/examples/basic/just_locator_example.py
just_agents/examples/basic/just_tools_example.py
just_agents/examples/basic/logging_redirection_simple.py
just_agents/examples/basic/perplexity.py
just_agents/examples/coding/__init__.py
just_agents/examples/coding/bioinformatic_collab.py
just_agents/examples/coding/bioinformatic_dev_agent.yaml
just_agents/examples/coding/chain_of_though_coding_agent.py
just_agents/examples/coding/coding_agents.yaml
just_agents/examples/coding/cot_dev.py
just_agents/examples/coding/cot_dev_agent_profiles.yaml
just_agents/examples/coding/cot_memory.py
just_agents/examples/coding/devops_agent.yaml
just_agents/examples/coding/mounts.py
just_agents/examples/coding/schema_roundtrip_demo.py
just_agents/examples/coding/schema_validation_example.py
just_agents/examples/coding/simple_code_agent_.py
just_agents/examples/coding/tools.py
just_agents/examples/multiagent/__init__.py
just_agents/examples/multiagent/drug_example.py
just_agents/examples/multiagent/glucose_dao_reflection.py
just_agents/examples/multiagent/trump_and_camala_debate.py
just_agents/examples/tools.py
just_agents/examples/toy_mcp_servers/__init__.py
just_agents/examples/toy_mcp_servers/bip_bop_server.py
just_agents/examples/toy_mcp_servers/mcp_stdio_server.py
just_agents/examples/web/__init__.py
just_agents/examples/web/agent_profiles.yaml
just_agents/examples/web/chat_agent_profiles.yaml
just_agents/examples/web/nice_agent_chat_ui_config.env
just_agents/examples/web/nice_web.py
just_agents_examples-0.8.7.dist-info/METADATA
just_agents_examples-0.8.7.dist-info/WHEEL
just_agents_examples-0.8.7.dist-info/RECORD
