Metadata-Version: 2.4
Name: just-agents-examples
Version: 0.8.7
Summary: Just Agents - Examples code
License: MIT
Author: Alex Karmazin
Author-email: karmazinalex@gmail.com
Maintainer: Anton Kulaga
Maintainer-email: antonkulaga@gmail.com
Requires-Python: >=3.10,<3.15
Classifier: License :: OSI Approved :: MIT License
Classifier: Programming Language :: Python :: 3
Classifier: Programming Language :: Python :: 3.10
Classifier: Programming Language :: Python :: 3.11
Classifier: Programming Language :: Python :: 3.12
Classifier: Programming Language :: Python :: 3.13
Classifier: Programming Language :: Python :: 3.14
Requires-Dist: coolname (>=2.2.0)
Requires-Dist: fastmcp (>=2.2.10)
Requires-Dist: just-agents-coding
Requires-Dist: just-agents-router
Requires-Dist: just-agents-tools
Requires-Dist: just-agents-web
